nsanic/__init__.py
nsanic/base_blue.py
nsanic/base_conf.py
nsanic/base_server.py
nsanic/base_ws.py
nsanic/exception.py
nsanic/handler_http.py
nsanic/handler_ws.py
nsanic/middleware.py
nsanic/mult_creator.py
nsanic/verify.py
nsanic/libs/__init__.py
nsanic/libs/base_timed.py
nsanic/libs/base_ws_srv.py
nsanic/libs/component.py
nsanic/libs/consts.py
nsanic/libs/crypto.py
nsanic/libs/db_client.py
nsanic/libs/decorator.py
nsanic/libs/file_type.py
nsanic/libs/manager.py
nsanic/libs/mk_random.py
nsanic/libs/mult_log.py
nsanic/libs/rds_client.py
nsanic/libs/rds_locker.py
nsanic/libs/tool.py
nsanic/libs/tool_dt.py
nsanic/libs/tool_jwt.py
nsanic/libs/tool_ws.py
nsanic/orm/__init__.py
nsanic/orm/db_index.py
nsanic/orm/db_model.py
nsanic/orm/mssql_generator.py
nsanic/orm/mysql_generator.py
nsanic/orm/pgsql_generator.py
nsanic/orm/rc_model.py
nsanic-2025.6.15.dist-info/licenses/LICENSE
test/__init__.py
test/test_unit.py
nsanic-2025.6.15.dist-info/METADATA
nsanic-2025.6.15.dist-info/WHEEL
nsanic-2025.6.15.dist-info/entry_points.txt
nsanic-2025.6.15.dist-info/top_level.txt
nsanic-2025.6.15.dist-info/RECORD
