Metadata-Version: 2.4
Name: nsanic
Version: 2025.6.15
Summary: A web framework who is use sanic + tortoise-orm + redis to quick create http&websocket server.
Author: DHDONG
Author-email: zscych@qq.com
License: MIT
Keywords: WebServer,Sanic,WebSite Develop,Web Framework
Classifier: Programming Language :: Python :: 3.9
Classifier: Programming Language :: Python :: 3.10
Classifier: Programming Language :: Python :: 3.11
Classifier: Programming Language :: Python :: 3.12
Classifier: Programming Language :: Python :: 3.13
Requires-Python: >=3.9
License-File: LICENSE
Requires-Dist: sanic>=22.12.0
Requires-Dist: redis[hiredis]>=4.6.0
Requires-Dist: pyjwt>=0.2.6
Requires-Dist: httpx>=0.23.0
Requires-Dist: orjson>=3.9.15
Dynamic: author
Dynamic: author-email
Dynamic: classifier
Dynamic: description
Dynamic: description-content-type
Dynamic: keywords
Dynamic: license
Dynamic: license-file
Dynamic: requires-dist
Dynamic: requires-python
Dynamic: summary
